README
neutrino.py
setup.py
neutrino.egg-info/PKG-INFO
neutrino.egg-info/SOURCES.txt
neutrino.egg-info/dependency_links.txt
neutrino.egg-info/requires.txt
neutrino.egg-info/top_level.txt