Metadata-Version: 1.0
Name: neutrino
Version: 0.2
Summary: High Performance Redis Timeseries
Home-page: https://github.com/tlatorre-uchicago/neutrino
Author: Anthony LaTorre
Author-email: UNKNOWN
License: UNKNOWN
Keywords: redis,timeseries
Platform: UNKNOWN
